Workbook

Sheet Calculo
A1: Financiamento: Price x SAC
A2: Preencha apenas as celulas amarelas. O resto e calculado.
A3: Fonte: Tabela Price e SAC, juros compostos mensais sobre o saldo devedor
A4: Estimativa para fins informativos; nao e aconselhamento juridico ou financeiro. Confira a fonte oficial e a convencao coletiva da sua categoria.
A6: Valor financiado | B6: 100000
A7: Taxa de juros mensal (%) | B7: 1
A8: Prazo (meses, ate 360) | B8: 12
A10: Price: parcela fixa | B10: =IF(B7=0,B6/B8,B6*(B7/100)/(1-(1+B7/100)^(-B8))) -> 8884.8789
A11: Price: total pago | B11: =B10*B8 -> 106618.55
A12: Price: juros totais | B12: =B11-B6 -> 6618.5464
A13: SAC: primeira parcela | B13: =B6/B8+B6*B7/100 -> 9333.3333
A14: SAC: ultima parcela | B14: =B6/B8+(B6/B8)*B7/100 -> 8416.6667
A15: SAC: total pago | B15: =B6+B6*(B7/100)*(B8+1)/2 -> 106500
A16: SAC: juros totais | B16: =B15-B6 -> 6500
A17: Diferenca de juros (Price - SAC) | B17: =B12-B16 -> 118.54641 | C17: Sem IOF, seguros e tarifas

Sheet Parcelas
A1: Mes | B1: Saldo SAC | C1: Parcela SAC | D1: Saldo Price | E1: Parcela Price
A2: =IF(1<=Calculo!$B$8,1,"") -> 1 | B2: =IF(A2="","",Calculo!$B$6) -> 100000 | C2: =IF(A2="","",Calculo!$B$6/Calculo!$B$8+B2*Calculo!$B$7/100) -> 9333.3333 | D2: =IF(A2="","",Calculo!$B$6) -> 100000 | E2: =IF(A2="","",Calculo!$B$10) -> 8884.8789
A3: =IF(2<=Calculo!$B$8,2,"") -> 2 | B3: =IF(A3="","",B2-Calculo!$B$6/Calculo!$B$8) -> 91666.667 | C3: =IF(A3="","",Calculo!$B$6/Calculo!$B$8+B3*Calculo!$B$7/100) -> 9250 | D3: =IF(A3="","",D2-(Calculo!$B$10-D2*Calculo!$B$7/100)) -> 92115.121 | E3: =IF(A3="","",Calculo!$B$10) -> 8884.8789
A4: =IF(3<=Calculo!$B$8,3,"") -> 3 | B4: =IF(A4="","",B3-Calculo!$B$6/Calculo!$B$8) -> 83333.333 | C4: =IF(A4="","",Calculo!$B$6/Calculo!$B$8+B4*Calculo!$B$7/100) -> 9166.6667 | D4: =IF(A4="","",D3-(Calculo!$B$10-D3*Calculo!$B$7/100)) -> 84151.393 | E4: =IF(A4="","",Calculo!$B$10) -> 8884.8789
A5: =IF(4<=Calculo!$B$8,4,"") -> 4 | B5: =IF(A5="","",B4-Calculo!$B$6/Calculo!$B$8) -> 75000 | C5: =IF(A5="","",Calculo!$B$6/Calculo!$B$8+B5*Calculo!$B$7/100) -> 9083.3333 | D5: =IF(A5="","",D4-(Calculo!$B$10-D4*Calculo!$B$7/100)) -> 76108.029 | E5: =IF(A5="","",Calculo!$B$10) -> 8884.8789
A6: =IF(5<=Calculo!$B$8,5,"") -> 5 | B6: =IF(A6="","",B5-Calculo!$B$6/Calculo!$B$8) -> 66666.667 | C6: =IF(A6="","",Calculo!$B$6/Calculo!$B$8+B6*Calculo!$B$7/100) -> 9000 | D6: =IF(A6="","",D5-(Calculo!$B$10-D5*Calculo!$B$7/100)) -> 67984.23 | E6: =IF(A6="","",Calculo!$B$10) -> 8884.8789
A7: =IF(6<=Calculo!$B$8,6,"") -> 6 | B7: =IF(A7="","",B6-Calculo!$B$6/Calculo!$B$8) -> 58333.333 | C7: =IF(A7="","",Calculo!$B$6/Calculo!$B$8+B7*Calculo!$B$7/100) -> 8916.6667 | D7: =IF(A7="","",D6-(Calculo!$B$10-D6*Calculo!$B$7/100)) -> 59779.193 | E7: =IF(A7="","",Calculo!$B$10) -> 8884.8789
A8: =IF(7<=Calculo!$B$8,7,"") -> 7 | B8: =IF(A8="","",B7-Calculo!$B$6/Calculo!$B$8) -> 50000 | C8: =IF(A8="","",Calculo!$B$6/Calculo!$B$8+B8*Calculo!$B$7/100) -> 8833.3333 | D8: =IF(A8="","",D7-(Calculo!$B$10-D7*Calculo!$B$7/100)) -> 51492.106 | E8: =IF(A8="","",Calculo!$B$10) -> 8884.8789
A9: =IF(8<=Calculo!$B$8,8,"") -> 8 | B9: =IF(A9="","",B8-Calculo!$B$6/Calculo!$B$8) -> 41666.667 | C9: =IF(A9="","",Calculo!$B$6/Calculo!$B$8+B9*Calculo!$B$7/100) -> 8750 | D9: =IF(A9="","",D8-(Calculo!$B$10-D8*Calculo!$B$7/100)) -> 43122.149 | E9: =IF(A9="","",Calculo!$B$10) -> 8884.8789
A10: =IF(9<=Calculo!$B$8,9,"") -> 9 | B10: =IF(A10="","",B9-Calculo!$B$6/Calculo!$B$8) -> 33333.333 | C10: =IF(A10="","",Calculo!$B$6/Calculo!$B$8+B10*Calculo!$B$7/100) -> 8666.6667 | D10: =IF(A10="","",D9-(Calculo!$B$10-D9*Calculo!$B$7/100)) -> 34668.491 | E10: =IF(A10="","",Calculo!$B$10) -> 8884.8789
A11: =IF(10<=Calculo!$B$8,10,"") -> 10 | B11: =IF(A11="","",B10-Calculo!$B$6/Calculo!$B$8) -> 25000 | C11: =IF(A11="","",Calculo!$B$6/Calculo!$B$8+B11*Calculo!$B$7/100) -> 8583.3333 | D11: =IF(A11="","",D10-(Calculo!$B$10-D10*Calculo!$B$7/100)) -> 26130.297 | E11: =IF(A11="","",Calculo!$B$10) -> 8884.8789
A12: =IF(11<=Calculo!$B$8,11,"") -> 11 | B12: =IF(A12="","",B11-Calculo!$B$6/Calculo!$B$8) -> 16666.667 | C12: =IF(A12="","",Calculo!$B$6/Calculo!$B$8+B12*Calculo!$B$7/100) -> 8500 | D12: =IF(A12="","",D11-(Calculo!$B$10-D11*Calculo!$B$7/100)) -> 17506.721 | E12: =IF(A12="","",Calculo!$B$10) -> 8884.8789
A13: =IF(12<=Calculo!$B$8,12,"") -> 12 | B13: =IF(A13="","",B12-Calculo!$B$6/Calculo!$B$8) -> 8333.3333 | C13: =IF(A13="","",Calculo!$B$6/Calculo!$B$8+B13*Calculo!$B$7/100) -> 8416.6667 | D13: =IF(A13="","",D12-(Calculo!$B$10-D12*Calculo!$B$7/100)) -> 8796.9098 | E13: =IF(A13="","",Calculo!$B$10) -> 8884.8789
A14: =IF(13<=Calculo!$B$8,13,"") | B14: =IF(A14="","",B13-Calculo!$B$6/Calculo!$B$8) | C14: =IF(A14="","",Calculo!$B$6/Calculo!$B$8+B14*Calculo!$B$7/100) | D14: =IF(A14="","",D13-(Calculo!$B$10-D13*Calculo!$B$7/100)) | E14: =IF(A14="","",Calculo!$B$10)
A15: =IF(14<=Calculo!$B$8,14,"") | B15: =IF(A15="","",B14-Calculo!$B$6/Calculo!$B$8) | C15: =IF(A15="","",Calculo!$B$6/Calculo!$B$8+B15*Calculo!$B$7/100) | D15: =IF(A15="","",D14-(Calculo!$B$10-D14*Calculo!$B$7/100)) | E15: =IF(A15="","",Calculo!$B$10)
A16: =IF(15<=Calculo!$B$8,15,"") | B16: =IF(A16="","",B15-Calculo!$B$6/Calculo!$B$8) | C16: =IF(A16="","",Calculo!$B$6/Calculo!$B$8+B16*Calculo!$B$7/100) | D16: =IF(A16="","",D15-(Calculo!$B$10-D15*Calculo!$B$7/100)) | E16: =IF(A16="","",Calculo!$B$10)
A17: =IF(16<=Calculo!$B$8,16,"") | B17: =IF(A17="","",B16-Calculo!$B$6/Calculo!$B$8) | C17: =IF(A17="","",Calculo!$B$6/Calculo!$B$8+B17*Calculo!$B$7/100) | D17: =IF(A17="","",D16-(Calculo!$B$10-D16*Calculo!$B$7/100)) | E17: =IF(A17="","",Calculo!$B$10)
A18: =IF(17<=Calculo!$B$8,17,"") | B18: =IF(A18="","",B17-Calculo!$B$6/Calculo!$B$8) | C18: =IF(A18="","",Calculo!$B$6/Calculo!$B$8+B18*Calculo!$B$7/100) | D18: =IF(A18="","",D17-(Calculo!$B$10-D17*Calculo!$B$7/100)) | E18: =IF(A18="","",Calculo!$B$10)
A19: =IF(18<=Calculo!$B$8,18,"") | B19: =IF(A19="","",B18-Calculo!$B$6/Calculo!$B$8) | C19: =IF(A19="","",Calculo!$B$6/Calculo!$B$8+B19*Calculo!$B$7/100) | D19: =IF(A19="","",D18-(Calculo!$B$10-D18*Calculo!$B$7/100)) | E19: =IF(A19="","",Calculo!$B$10)
A20: =IF(19<=Calculo!$B$8,19,"") | B20: =IF(A20="","",B19-Calculo!$B$6/Calculo!$B$8) | C20: =IF(A20="","",Calculo!$B$6/Calculo!$B$8+B20*Calculo!$B$7/100) | D20: =IF(A20="","",D19-(Calculo!$B$10-D19*Calculo!$B$7/100)) | E20: =IF(A20="","",Calculo!$B$10)
A21: =IF(20<=Calculo!$B$8,20,"") | B21: =IF(A21="","",B20-Calculo!$B$6/Calculo!$B$8) | C21: =IF(A21="","",Calculo!$B$6/Calculo!$B$8+B21*Calculo!$B$7/100) | D21: =IF(A21="","",D20-(Calculo!$B$10-D20*Calculo!$B$7/100)) | E21: =IF(A21="","",Calculo!$B$10)
A22: =IF(21<=Calculo!$B$8,21,"") | B22: =IF(A22="","",B21-Calculo!$B$6/Calculo!$B$8) | C22: =IF(A22="","",Calculo!$B$6/Calculo!$B$8+B22*Calculo!$B$7/100) | D22: =IF(A22="","",D21-(Calculo!$B$10-D21*Calculo!$B$7/100)) | E22: =IF(A22="","",Calculo!$B$10)
A23: =IF(22<=Calculo!$B$8,22,"") | B23: =IF(A23="","",B22-Calculo!$B$6/Calculo!$B$8) | C23: =IF(A23="","",Calculo!$B$6/Calculo!$B$8+B23*Calculo!$B$7/100) | D23: =IF(A23="","",D22-(Calculo!$B$10-D22*Calculo!$B$7/100)) | E23: =IF(A23="","",Calculo!$B$10)
A24: =IF(23<=Calculo!$B$8,23,"") | B24: =IF(A24="","",B23-Calculo!$B$6/Calculo!$B$8) | C24: =IF(A24="","",Calculo!$B$6/Calculo!$B$8+B24*Calculo!$B$7/100) | D24: =IF(A24="","",D23-(Calculo!$B$10-D23*Calculo!$B$7/100)) | E24: =IF(A24="","",Calculo!$B$10)
A25: =IF(24<=Calculo!$B$8,24,"") | B25: =IF(A25="","",B24-Calculo!$B$6/Calculo!$B$8) | C25: =IF(A25="","",Calculo!$B$6/Calculo!$B$8+B25*Calculo!$B$7/100) | D25: =IF(A25="","",D24-(Calculo!$B$10-D24*Calculo!$B$7/100)) | E25: =IF(A25="","",Calculo!$B$10)
A26: =IF(25<=Calculo!$B$8,25,"") | B26: =IF(A26="","",B25-Calculo!$B$6/Calculo!$B$8) | C26: =IF(A26="","",Calculo!$B$6/Calculo!$B$8+B26*Calculo!$B$7/100) | D26: =IF(A26="","",D25-(Calculo!$B$10-D25*Calculo!$B$7/100)) | E26: =IF(A26="","",Calculo!$B$10)
A27: =IF(26<=Calculo!$B$8,26,"") | B27: =IF(A27="","",B26-Calculo!$B$6/Calculo!$B$8) | C27: =IF(A27="","",Calculo!$B$6/Calculo!$B$8+B27*Calculo!$B$7/100) | D27: =IF(A27="","",D26-(Calculo!$B$10-D26*Calculo!$B$7/100)) | E27: =IF(A27="","",Calculo!$B$10)
A28: =IF(27<=Calculo!$B$8,27,"") | B28: =IF(A28="","",B27-Calculo!$B$6/Calculo!$B$8) | C28: =IF(A28="","",Calculo!$B$6/Calculo!$B$8+B28*Calculo!$B$7/100) | D28: =IF(A28="","",D27-(Calculo!$B$10-D27*Calculo!$B$7/100)) | E28: =IF(A28="","",Calculo!$B$10)
A29: =IF(28<=Calculo!$B$8,28,"") | B29: =IF(A29="","",B28-Calculo!$B$6/Calculo!$B$8) | C29: =IF(A29="","",Calculo!$B$6/Calculo!$B$8+B29*Calculo!$B$7/100) | D29: =IF(A29="","",D28-(Calculo!$B$10-D28*Calculo!$B$7/100)) | E29: =IF(A29="","",Calculo!$B$10)
A30: =IF(29<=Calculo!$B$8,29,"") | B30: =IF(A30="","",B29-Calculo!$B$6/Calculo!$B$8) | C30: =IF(A30="","",Calculo!$B$6/Calculo!$B$8+B30*Calculo!$B$7/100) | D30: =IF(A30="","",D29-(Calculo!$B$10-D29*Calculo!$B$7/100)) | E30: =IF(A30="","",Calculo!$B$10)
A31: =IF(30<=Calculo!$B$8,30,"") | B31: =IF(A31="","",B30-Calculo!$B$6/Calculo!$B$8) | C31: =IF(A31="","",Calculo!$B$6/Calculo!$B$8+B31*Calculo!$B$7/100) | D31: =IF(A31="","",D30-(Calculo!$B$10-D30*Calculo!$B$7/100)) | E31: =IF(A31="","",Calculo!$B$10)
A32: =IF(31<=Calculo!$B$8,31,"") | B32: =IF(A32="","",B31-Calculo!$B$6/Calculo!$B$8) | C32: =IF(A32="","",Calculo!$B$6/Calculo!$B$8+B32*Calculo!$B$7/100) | D32: =IF(A32="","",D31-(Calculo!$B$10-D31*Calculo!$B$7/100)) | E32: =IF(A32="","",Calculo!$B$10)
A33: =IF(32<=Calculo!$B$8,32,"") | B33: =IF(A33="","",B32-Calculo!$B$6/Calculo!$B$8) | C33: =IF(A33="","",Calculo!$B$6/Calculo!$B$8+B33*Calculo!$B$7/100) | D33: =IF(A33="","",D32-(Calculo!$B$10-D32*Calculo!$B$7/100)) | E33: =IF(A33="","",Calculo!$B$10)
A34: =IF(33<=Calculo!$B$8,33,"") | B34: =IF(A34="","",B33-Calculo!$B$6/Calculo!$B$8) | C34: =IF(A34="","",Calculo!$B$6/Calculo!$B$8+B34*Calculo!$B$7/100) | D34: =IF(A34="","",D33-(Calculo!$B$10-D33*Calculo!$B$7/100)) | E34: =IF(A34="","",Calculo!$B$10)
A35: =IF(34<=Calculo!$B$8,34,"") | B35: =IF(A35="","",B34-Calculo!$B$6/Calculo!$B$8) | C35: =IF(A35="","",Calculo!$B$6/Calculo!$B$8+B35*Calculo!$B$7/100) | D35: =IF(A35="","",D34-(Calculo!$B$10-D34*Calculo!$B$7/100)) | E35: =IF(A35="","",Calculo!$B$10)
A36: =IF(35<=Calculo!$B$8,35,"") | B36: =IF(A36="","",B35-Calculo!$B$6/Calculo!$B$8) | C36: =IF(A36="","",Calculo!$B$6/Calculo!$B$8+B36*Calculo!$B$7/100) | D36: =IF(A36="","",D35-(Calculo!$B$10-D35*Calculo!$B$7/100)) | E36: =IF(A36="","",Calculo!$B$10)
A37: =IF(36<=Calculo!$B$8,36,"") | B37: =IF(A37="","",B36-Calculo!$B$6/Calculo!$B$8) | C37: =IF(A37="","",Calculo!$B$6/Calculo!$B$8+B37*Calculo!$B$7/100) | D37: =IF(A37="","",D36-(Calculo!$B$10-D36*Calculo!$B$7/100)) | E37: =IF(A37="","",Calculo!$B$10)
A38: =IF(37<=Calculo!$B$8,37,"") | B38: =IF(A38="","",B37-Calculo!$B$6/Calculo!$B$8) | C38: =IF(A38="","",Calculo!$B$6/Calculo!$B$8+B38*Calculo!$B$7/100) | D38: =IF(A38="","",D37-(Calculo!$B$10-D37*Calculo!$B$7/100)) | E38: =IF(A38="","",Calculo!$B$10)
A39: =IF(38<=Calculo!$B$8,38,"") | B39: =IF(A39="","",B38-Calculo!$B$6/Calculo!$B$8) | C39: =IF(A39="","",Calculo!$B$6/Calculo!$B$8+B39*Calculo!$B$7/100) | D39: =IF(A39="","",D38-(Calculo!$B$10-D38*Calculo!$B$7/100)) | E39: =IF(A39="","",Calculo!$B$10)
A40: =IF(39<=Calculo!$B$8,39,"") | B40: =IF(A40="","",B39-Calculo!$B$6/Calculo!$B$8) | C40: =IF(A40="","",Calculo!$B$6/Calculo!$B$8+B40*Calculo!$B$7/100) | D40: =IF(A40="","",D39-(Calculo!$B$10-D39*Calculo!$B$7/100)) | E40: =IF(A40="","",Calculo!$B$10)
A41: =IF(40<=Calculo!$B$8,40,"") | B41: =IF(A41="","",B40-Calculo!$B$6/Calculo!$B$8) | C41: =IF(A41="","",Calculo!$B$6/Calculo!$B$8+B41*Calculo!$B$7/100) | D41: =IF(A41="","",D40-(Calculo!$B$10-D40*Calculo!$B$7/100)) | E41: =IF(A41="","",Calculo!$B$10)
A42: =IF(41<=Calculo!$B$8,41,"") | B42: =IF(A42="","",B41-Calculo!$B$6/Calculo!$B$8) | C42: =IF(A42="","",Calculo!$B$6/Calculo!$B$8+B42*Calculo!$B$7/100) | D42: =IF(A42="","",D41-(Calculo!$B$10-D41*Calculo!$B$7/100)) | E42: =IF(A42="","",Calculo!$B$10)
A43: =IF(42<=Calculo!$B$8,42,"") | B43: =IF(A43="","",B42-Calculo!$B$6/Calculo!$B$8) | C43: =IF(A43="","",Calculo!$B$6/Calculo!$B$8+B43*Calculo!$B$7/100) | D43: =IF(A43="","",D42-(Calculo!$B$10-D42*Calculo!$B$7/100)) | E43: =IF(A43="","",Calculo!$B$10)
A44: =IF(43<=Calculo!$B$8,43,"") | B44: =IF(A44="","",B43-Calculo!$B$6/Calculo!$B$8) | C44: =IF(A44="","",Calculo!$B$6/Calculo!$B$8+B44*Calculo!$B$7/100) | D44: =IF(A44="","",D43-(Calculo!$B$10-D43*Calculo!$B$7/100)) | E44: =IF(A44="","",Calculo!$B$10)
A45: =IF(44<=Calculo!$B$8,44,"") | B45: =IF(A45="","",B44-Calculo!$B$6/Calculo!$B$8) | C45: =IF(A45="","",Calculo!$B$6/Calculo!$B$8+B45*Calculo!$B$7/100) | D45: =IF(A45="","",D44-(Calculo!$B$10-D44*Calculo!$B$7/100)) | E45: =IF(A45="","",Calculo!$B$10)
A46: =IF(45<=Calculo!$B$8,45,"") | B46: =IF(A46="","",B45-Calculo!$B$6/Calculo!$B$8) | C46: =IF(A46="","",Calculo!$B$6/Calculo!$B$8+B46*Calculo!$B$7/100) | D46: =IF(A46="","",D45-(Calculo!$B$10-D45*Calculo!$B$7/100)) | E46: =IF(A46="","",Calculo!$B$10)
A47: =IF(46<=Calculo!$B$8,46,"") | B47: =IF(A47="","",B46-Calculo!$B$6/Calculo!$B$8) | C47: =IF(A47="","",Calculo!$B$6/Calculo!$B$8+B47*Calculo!$B$7/100) | D47: =IF(A47="","",D46-(Calculo!$B$10-D46*Calculo!$B$7/100)) | E47: =IF(A47="","",Calculo!$B$10)
A48: =IF(47<=Calculo!$B$8,47,"") | B48: =IF(A48="","",B47-Calculo!$B$6/Calculo!$B$8) | C48: =IF(A48="","",Calculo!$B$6/Calculo!$B$8+B48*Calculo!$B$7/100) | D48: =IF(A48="","",D47-(Calculo!$B$10-D47*Calculo!$B$7/100)) | E48: =IF(A48="","",Calculo!$B$10)
A49: =IF(48<=Calculo!$B$8,48,"") | B49: =IF(A49="","",B48-Calculo!$B$6/Calculo!$B$8) | C49: =IF(A49="","",Calculo!$B$6/Calculo!$B$8+B49*Calculo!$B$7/100) | D49: =IF(A49="","",D48-(Calculo!$B$10-D48*Calculo!$B$7/100)) | E49: =IF(A49="","",Calculo!$B$10)
A50: =IF(49<=Calculo!$B$8,49,"") | B50: =IF(A50="","",B49-Calculo!$B$6/Calculo!$B$8) | C50: =IF(A50="","",Calculo!$B$6/Calculo!$B$8+B50*Calculo!$B$7/100) | D50: =IF(A50="","",D49-(Calculo!$B$10-D49*Calculo!$B$7/100)) | E50: =IF(A50="","",Calculo!$B$10)
A51: =IF(50<=Calculo!$B$8,50,"") | B51: =IF(A51="","",B50-Calculo!$B$6/Calculo!$B$8) | C51: =IF(A51="","",Calculo!$B$6/Calculo!$B$8+B51*Calculo!$B$7/100) | D51: =IF(A51="","",D50-(Calculo!$B$10-D50*Calculo!$B$7/100)) | E51: =IF(A51="","",Calculo!$B$10)
A52: =IF(51<=Calculo!$B$8,51,"") | B52: =IF(A52="","",B51-Calculo!$B$6/Calculo!$B$8) | C52: =IF(A52="","",Calculo!$B$6/Calculo!$B$8+B52*Calculo!$B$7/100) | D52: =IF(A52="","",D51-(Calculo!$B$10-D51*Calculo!$B$7/100)) | E52: =IF(A52="","",Calculo!$B$10)
A53: =IF(52<=Calculo!$B$8,52,"") | B53: =IF(A53="","",B52-Calculo!$B$6/Calculo!$B$8) | C53: =IF(A53="","",Calculo!$B$6/Calculo!$B$8+B53*Calculo!$B$7/100) | D53: =IF(A53="","",D52-(Calculo!$B$10-D52*Calculo!$B$7/100)) | E53: =IF(A53="","",Calculo!$B$10)
A54: =IF(53<=Calculo!$B$8,53,"") | B54: =IF(A54="","",B53-Calculo!$B$6/Calculo!$B$8) | C54: =IF(A54="","",Calculo!$B$6/Calculo!$B$8+B54*Calculo!$B$7/100) | D54: =IF(A54="","",D53-(Calculo!$B$10-D53*Calculo!$B$7/100)) | E54: =IF(A54="","",Calculo!$B$10)
A55: =IF(54<=Calculo!$B$8,54,"") | B55: =IF(A55="","",B54-Calculo!$B$6/Calculo!$B$8) | C55: =IF(A55="","",Calculo!$B$6/Calculo!$B$8+B55*Calculo!$B$7/100) | D55: =IF(A55="","",D54-(Calculo!$B$10-D54*Calculo!$B$7/100)) | E55: =IF(A55="","",Calculo!$B$10)
A56: =IF(55<=Calculo!$B$8,55,"") | B56: =IF(A56="","",B55-Calculo!$B$6/Calculo!$B$8) | C56: =IF(A56="","",Calculo!$B$6/Calculo!$B$8+B56*Calculo!$B$7/100) | D56: =IF(A56="","",D55-(Calculo!$B$10-D55*Calculo!$B$7/100)) | E56: =IF(A56="","",Calculo!$B$10)
A57: =IF(56<=Calculo!$B$8,56,"") | B57: =IF(A57="","",B56-Calculo!$B$6/Calculo!$B$8) | C57: =IF(A57="","",Calculo!$B$6/Calculo!$B$8+B57*Calculo!$B$7/100) | D57: =IF(A57="","",D56-(Calculo!$B$10-D56*Calculo!$B$7/100)) | E57: =IF(A57="","",Calculo!$B$10)
A58: =IF(57<=Calculo!$B$8,57,"") | B58: =IF(A58="","",B57-Calculo!$B$6/Calculo!$B$8) | C58: =IF(A58="","",Calculo!$B$6/Calculo!$B$8+B58*Calculo!$B$7/100) | D58: =IF(A58="","",D57-(Calculo!$B$10-D57*Calculo!$B$7/100)) | E58: =IF(A58="","",Calculo!$B$10)
A59: =IF(58<=Calculo!$B$8,58,"") | B59: =IF(A59="","",B58-Calculo!$B$6/Calculo!$B$8) | C59: =IF(A59="","",Calculo!$B$6/Calculo!$B$8+B59*Calculo!$B$7/100) | D59: =IF(A59="","",D58-(Calculo!$B$10-D58*Calculo!$B$7/100)) | E59: =IF(A59="","",Calculo!$B$10)
A60: =IF(59<=Calculo!$B$8,59,"") | B60: =IF(A60="","",B59-Calculo!$B$6/Calculo!$B$8) | C60: =IF(A60="","",Calculo!$B$6/Calculo!$B$8+B60*Calculo!$B$7/100) | D60: =IF(A60="","",D59-(Calculo!$B$10-D59*Calculo!$B$7/100)) | E60: =IF(A60="","",Calculo!$B$10)
A61: =IF(60<=Calculo!$B$8,60,"") | B61: =IF(A61="","",B60-Calculo!$B$6/Calculo!$B$8) | C61: =IF(A61="","",Calculo!$B$6/Calculo!$B$8+B61*Calculo!$B$7/100) | D61: =IF(A61="","",D60-(Calculo!$B$10-D60*Calculo!$B$7/100)) | E61: =IF(A61="","",Calculo!$B$10)
A62: =IF(61<=Calculo!$B$8,61,"") | B62: =IF(A62="","",B61-Calculo!$B$6/Calculo!$B$8) | C62: =IF(A62="","",Calculo!$B$6/Calculo!$B$8+B62*Calculo!$B$7/100) | D62: =IF(A62="","",D61-(Calculo!$B$10-D61*Calculo!$B$7/100)) | E62: =IF(A62="","",Calculo!$B$10)
A63: =IF(62<=Calculo!$B$8,62,"") | B63: =IF(A63="","",B62-Calculo!$B$6/Calculo!$B$8) | C63: =IF(A63="","",Calculo!$B$6/Calculo!$B$8+B63*Calculo!$B$7/100) | D63: =IF(A63="","",D62-(Calculo!$B$10-D62*Calculo!$B$7/100)) | E63: =IF(A63="","",Calculo!$B$10)
A64: =IF(63<=Calculo!$B$8,63,"") | B64: =IF(A64="","",B63-Calculo!$B$6/Calculo!$B$8) | C64: =IF(A64="","",Calculo!$B$6/Calculo!$B$8+B64*Calculo!$B$7/100) | D64: =IF(A64="","",D63-(Calculo!$B$10-D63*Calculo!$B$7/100)) | E64: =IF(A64="","",Calculo!$B$10)
A65: =IF(64<=Calculo!$B$8,64,"") | B65: =IF(A65="","",B64-Calculo!$B$6/Calculo!$B$8) | C65: =IF(A65="","",Calculo!$B$6/Calculo!$B$8+B65*Calculo!$B$7/100) | D65: =IF(A65="","",D64-(Calculo!$B$10-D64*Calculo!$B$7/100)) | E65: =IF(A65="","",Calculo!$B$10)
A66: =IF(65<=Calculo!$B$8,65,"") | B66: =IF(A66="","",B65-Calculo!$B$6/Calculo!$B$8) | C66: =IF(A66="","",Calculo!$B$6/Calculo!$B$8+B66*Calculo!$B$7/100) | D66: =IF(A66="","",D65-(Calculo!$B$10-D65*Calculo!$B$7/100)) | E66: =IF(A66="","",Calculo!$B$10)
A67: =IF(66<=Calculo!$B$8,66,"") | B67: =IF(A67="","",B66-Calculo!$B$6/Calculo!$B$8) | C67: =IF(A67="","",Calculo!$B$6/Calculo!$B$8+B67*Calculo!$B$7/100) | D67: =IF(A67="","",D66-(Calculo!$B$10-D66*Calculo!$B$7/100)) | E67: =IF(A67="","",Calculo!$B$10)
A68: =IF(67<=Calculo!$B$8,67,"") | B68: =IF(A68="","",B67-Calculo!$B$6/Calculo!$B$8) | C68: =IF(A68="","",Calculo!$B$6/Calculo!$B$8+B68*Calculo!$B$7/100) | D68: =IF(A68="","",D67-(Calculo!$B$10-D67*Calculo!$B$7/100)) | E68: =IF(A68="","",Calculo!$B$10)
A69: =IF(68<=Calculo!$B$8,68,"") | B69: =IF(A69="","",B68-Calculo!$B$6/Calculo!$B$8) | C69: =IF(A69="","",Calculo!$B$6/Calculo!$B$8+B69*Calculo!$B$7/100) | D69: =IF(A69="","",D68-(Calculo!$B$10-D68*Calculo!$B$7/100)) | E69: =IF(A69="","",Calculo!$B$10)
A70: =IF(69<=Calculo!$B$8,69,"") | B70: =IF(A70="","",B69-Calculo!$B$6/Calculo!$B$8) | C70: =IF(A70="","",Calculo!$B$6/Calculo!$B$8+B70*Calculo!$B$7/100) | D70: =IF(A70="","",D69-(Calculo!$B$10-D69*Calculo!$B$7/100)) | E70: =IF(A70="","",Calculo!$B$10)
A71: =IF(70<=Calculo!$B$8,70,"") | B71: =IF(A71="","",B70-Calculo!$B$6/Calculo!$B$8) | C71: =IF(A71="","",Calculo!$B$6/Calculo!$B$8+B71*Calculo!$B$7/100) | D71: =IF(A71="","",D70-(Calculo!$B$10-D70*Calculo!$B$7/100)) | E71: =IF(A71="","",Calculo!$B$10)
A72: =IF(71<=Calculo!$B$8,71,"") | B72: =IF(A72="","",B71-Calculo!$B$6/Calculo!$B$8) | C72: =IF(A72="","",Calculo!$B$6/Calculo!$B$8+B72*Calculo!$B$7/100) | D72: =IF(A72="","",D71-(Calculo!$B$10-D71*Calculo!$B$7/100)) | E72: =IF(A72="","",Calculo!$B$10)
A73: =IF(72<=Calculo!$B$8,72,"") | B73: =IF(A73="","",B72-Calculo!$B$6/Calculo!$B$8) | C73: =IF(A73="","",Calculo!$B$6/Calculo!$B$8+B73*Calculo!$B$7/100) | D73: =IF(A73="","",D72-(Calculo!$B$10-D72*Calculo!$B$7/100)) | E73: =IF(A73="","",Calculo!$B$10)
A74: =IF(73<=Calculo!$B$8,73,"") | B74: =IF(A74="","",B73-Calculo!$B$6/Calculo!$B$8) | C74: =IF(A74="","",Calculo!$B$6/Calculo!$B$8+B74*Calculo!$B$7/100) | D74: =IF(A74="","",D73-(Calculo!$B$10-D73*Calculo!$B$7/100)) | E74: =IF(A74="","",Calculo!$B$10)
A75: =IF(74<=Calculo!$B$8,74,"") | B75: =IF(A75="","",B74-Calculo!$B$6/Calculo!$B$8) | C75: =IF(A75="","",Calculo!$B$6/Calculo!$B$8+B75*Calculo!$B$7/100) | D75: =IF(A75="","",D74-(Calculo!$B$10-D74*Calculo!$B$7/100)) | E75: =IF(A75="","",Calculo!$B$10)
A76: =IF(75<=Calculo!$B$8,75,"") | B76: =IF(A76="","",B75-Calculo!$B$6/Calculo!$B$8) | C76: =IF(A76="","",Calculo!$B$6/Calculo!$B$8+B76*Calculo!$B$7/100) | D76: =IF(A76="","",D75-(Calculo!$B$10-D75*Calculo!$B$7/100)) | E76: =IF(A76="","",Calculo!$B$10)
A77: =IF(76<=Calculo!$B$8,76,"") | B77: =IF(A77="","",B76-Calculo!$B$6/Calculo!$B$8) | C77: =IF(A77="","",Calculo!$B$6/Calculo!$B$8+B77*Calculo!$B$7/100) | D77: =IF(A77="","",D76-(Calculo!$B$10-D76*Calculo!$B$7/100)) | E77: =IF(A77="","",Calculo!$B$10)
A78: =IF(77<=Calculo!$B$8,77,"") | B78: =IF(A78="","",B77-Calculo!$B$6/Calculo!$B$8) | C78: =IF(A78="","",Calculo!$B$6/Calculo!$B$8+B78*Calculo!$B$7/100) | D78: =IF(A78="","",D77-(Calculo!$B$10-D77*Calculo!$B$7/100)) | E78: =IF(A78="","",Calculo!$B$10)
A79: =IF(78<=Calculo!$B$8,78,"") | B79: =IF(A79="","",B78-Calculo!$B$6/Calculo!$B$8) | C79: =IF(A79="","",Calculo!$B$6/Calculo!$B$8+B79*Calculo!$B$7/100) | D79: =IF(A79="","",D78-(Calculo!$B$10-D78*Calculo!$B$7/100)) | E79: =IF(A79="","",Calculo!$B$10)
A80: =IF(79<=Calculo!$B$8,79,"") | B80: =IF(A80="","",B79-Calculo!$B$6/Calculo!$B$8) | C80: =IF(A80="","",Calculo!$B$6/Calculo!$B$8+B80*Calculo!$B$7/100) | D80: =IF(A80="","",D79-(Calculo!$B$10-D79*Calculo!$B$7/100)) | E80: =IF(A80="","",Calculo!$B$10)
A81: =IF(80<=Calculo!$B$8,80,"") | B81: =IF(A81="","",B80-Calculo!$B$6/Calculo!$B$8) | C81: =IF(A81="","",Calculo!$B$6/Calculo!$B$8+B81*Calculo!$B$7/100) | D81: =IF(A81="","",D80-(Calculo!$B$10-D80*Calculo!$B$7/100)) | E81: =IF(A81="","",Calculo!$B$10)
A82: =IF(81<=Calculo!$B$8,81,"") | B82: =IF(A82="","",B81-Calculo!$B$6/Calculo!$B$8) | C82: =IF(A82="","",Calculo!$B$6/Calculo!$B$8+B82*Calculo!$B$7/100) | D82: =IF(A82="","",D81-(Calculo!$B$10-D81*Calculo!$B$7/100)) | E82: =IF(A82="","",Calculo!$B$10)
A83: =IF(82<=Calculo!$B$8,82,"") | B83: =IF(A83="","",B82-Calculo!$B$6/Calculo!$B$8) | C83: =IF(A83="","",Calculo!$B$6/Calculo!$B$8+B83*Calculo!$B$7/100) | D83: =IF(A83="","",D82-(Calculo!$B$10-D82*Calculo!$B$7/100)) | E83: =IF(A83="","",Calculo!$B$10)
A84: =IF(83<=Calculo!$B$8,83,"") | B84: =IF(A84="","",B83-Calculo!$B$6/Calculo!$B$8) | C84: =IF(A84="","",Calculo!$B$6/Calculo!$B$8+B84*Calculo!$B$7/100) | D84: =IF(A84="","",D83-(Calculo!$B$10-D83*Calculo!$B$7/100)) | E84: =IF(A84="","",Calculo!$B$10)
A85: =IF(84<=Calculo!$B$8,84,"") | B85: =IF(A85="","",B84-Calculo!$B$6/Calculo!$B$8) | C85: =IF(A85="","",Calculo!$B$6/Calculo!$B$8+B85*Calculo!$B$7/100) | D85: =IF(A85="","",D84-(Calculo!$B$10-D84*Calculo!$B$7/100)) | E85: =IF(A85="","",Calculo!$B$10)
A86: =IF(85<=Calculo!$B$8,85,"") | B86: =IF(A86="","",B85-Calculo!$B$6/Calculo!$B$8) | C86: =IF(A86="","",Calculo!$B$6/Calculo!$B$8+B86*Calculo!$B$7/100) | D86: =IF(A86="","",D85-(Calculo!$B$10-D85*Calculo!$B$7/100)) | E86: =IF(A86="","",Calculo!$B$10)
A87: =IF(86<=Calculo!$B$8,86,"") | B87: =IF(A87="","",B86-Calculo!$B$6/Calculo!$B$8) | C87: =IF(A87="","",Calculo!$B$6/Calculo!$B$8+B87*Calculo!$B$7/100) | D87: =IF(A87="","",D86-(Calculo!$B$10-D86*Calculo!$B$7/100)) | E87: =IF(A87="","",Calculo!$B$10)
A88: =IF(87<=Calculo!$B$8,87,"") | B88: =IF(A88="","",B87-Calculo!$B$6/Calculo!$B$8) | C88: =IF(A88="","",Calculo!$B$6/Calculo!$B$8+B88*Calculo!$B$7/100) | D88: =IF(A88="","",D87-(Calculo!$B$10-D87*Calculo!$B$7/100)) | E88: =IF(A88="","",Calculo!$B$10)
A89: =IF(88<=Calculo!$B$8,88,"") | B89: =IF(A89="","",B88-Calculo!$B$6/Calculo!$B$8) | C89: =IF(A89="","",Calculo!$B$6/Calculo!$B$8+B89*Calculo!$B$7/100) | D89: =IF(A89="","",D88-(Calculo!$B$10-D88*Calculo!$B$7/100)) | E89: =IF(A89="","",Calculo!$B$10)
A90: =IF(89<=Calculo!$B$8,89,"") | B90: =IF(A90="","",B89-Calculo!$B$6/Calculo!$B$8) | C90: =IF(A90="","",Calculo!$B$6/Calculo!$B$8+B90*Calculo!$B$7/100) | D90: =IF(A90="","",D89-(Calculo!$B$10-D89*Calculo!$B$7/100)) | E90: =IF(A90="","",Calculo!$B$10)
A91: =IF(90<=Calculo!$B$8,90,"") | B91: =IF(A91="","",B90-Calculo!$B$6/Calculo!$B$8) | C91: =IF(A91="","",Calculo!$B$6/Calculo!$B$8+B91*Calculo!$B$7/100) | D91: =IF(A91="","",D90-(Calculo!$B$10-D90*Calculo!$B$7/100)) | E91: =IF(A91="","",Calculo!$B$10)
A92: =IF(91<=Calculo!$B$8,91,"") | B92: =IF(A92="","",B91-Calculo!$B$6/Calculo!$B$8) | C92: =IF(A92="","",Calculo!$B$6/Calculo!$B$8+B92*Calculo!$B$7/100) | D92: =IF(A92="","",D91-(Calculo!$B$10-D91*Calculo!$B$7/100)) | E92: =IF(A92="","",Calculo!$B$10)
A93: =IF(92<=Calculo!$B$8,92,"") | B93: =IF(A93="","",B92-Calculo!$B$6/Calculo!$B$8) | C93: =IF(A93="","",Calculo!$B$6/Calculo!$B$8+B93*Calculo!$B$7/100) | D93: =IF(A93="","",D92-(Calculo!$B$10-D92*Calculo!$B$7/100)) | E93: =IF(A93="","",Calculo!$B$10)
A94: =IF(93<=Calculo!$B$8,93,"") | B94: =IF(A94="","",B93-Calculo!$B$6/Calculo!$B$8) | C94: =IF(A94="","",Calculo!$B$6/Calculo!$B$8+B94*Calculo!$B$7/100) | D94: =IF(A94="","",D93-(Calculo!$B$10-D93*Calculo!$B$7/100)) | E94: =IF(A94="","",Calculo!$B$10)
A95: =IF(94<=Calculo!$B$8,94,"") | B95: =IF(A95="","",B94-Calculo!$B$6/Calculo!$B$8) | C95: =IF(A95="","",Calculo!$B$6/Calculo!$B$8+B95*Calculo!$B$7/100) | D95: =IF(A95="","",D94-(Calculo!$B$10-D94*Calculo!$B$7/100)) | E95: =IF(A95="","",Calculo!$B$10)
A96: =IF(95<=Calculo!$B$8,95,"") | B96: =IF(A96="","",B95-Calculo!$B$6/Calculo!$B$8) | C96: =IF(A96="","",Calculo!$B$6/Calculo!$B$8+B96*Calculo!$B$7/100) | D96: =IF(A96="","",D95-(Calculo!$B$10-D95*Calculo!$B$7/100)) | E96: =IF(A96="","",Calculo!$B$10)
A97: =IF(96<=Calculo!$B$8,96,"") | B97: =IF(A97="","",B96-Calculo!$B$6/Calculo!$B$8) | C97: =IF(A97="","",Calculo!$B$6/Calculo!$B$8+B97*Calculo!$B$7/100) | D97: =IF(A97="","",D96-(Calculo!$B$10-D96*Calculo!$B$7/100)) | E97: =IF(A97="","",Calculo!$B$10)
A98: =IF(97<=Calculo!$B$8,97,"") | B98: =IF(A98="","",B97-Calculo!$B$6/Calculo!$B$8) | C98: =IF(A98="","",Calculo!$B$6/Calculo!$B$8+B98*Calculo!$B$7/100) | D98: =IF(A98="","",D97-(Calculo!$B$10-D97*Calculo!$B$7/100)) | E98: =IF(A98="","",Calculo!$B$10)
A99: =IF(98<=Calculo!$B$8,98,"") | B99: =IF(A99="","",B98-Calculo!$B$6/Calculo!$B$8) | C99: =IF(A99="","",Calculo!$B$6/Calculo!$B$8+B99*Calculo!$B$7/100) | D99: =IF(A99="","",D98-(Calculo!$B$10-D98*Calculo!$B$7/100)) | E99: =IF(A99="","",Calculo!$B$10)
A100: =IF(99<=Calculo!$B$8,99,"") | B100: =IF(A100="","",B99-Calculo!$B$6/Calculo!$B$8) | C100: =IF(A100="","",Calculo!$B$6/Calculo!$B$8+B100*Calculo!$B$7/100) | D100: =IF(A100="","",D99-(Calculo!$B$10-D99*Calculo!$B$7/100)) | E100: =IF(A100="","",Calculo!$B$10)
...
